[
    {
        "Title": "EU allies expel over 120 Russian diplomats in 2 days",
        "Full Article": "https://news.abs-cbn.com/overseas/04/05/22/eu-allies-expel-over-120-russian-diplomats-in-2-days",
        "Date and Time": "Apr 05 08:10 PM",
        "Author": " Ella Ide, Agence France-Presse "
    },
    {
        "Title": "Zelensky goes to Bucha, Ukraine",
        "Full Article": "https://news.abs-cbn.com/overseas/multimedia/photo/04/05/22/zelensky-goes-to-bucha-ukraine",
        "Date and Time": "Apr 05 05:10 PM",
        "Author": "Ronaldo Schemidt, AFP"
    },
    {
        "Title": "Indonesian teacher sentenced to death for raping 12 students",
        "Full Article": "https://news.abs-cbn.com/overseas/04/05/22/indonesian-teacher-sentenced-to-death-for-raping-12-students",
        "Date and Time": "Apr 05 04:33 PM",
        "Author": "Kyodo News"
    },
    {
        "Title": "'Several dead' in Hungary train crash: police",
        "Full Article": "https://news.abs-cbn.com/overseas/04/05/22/several-dead-in-hungary-train-crash-police",
        "Date and Time": "Apr 05 03:55 PM",
        "Author": "Agence France-Presse"
    },
    {
        "Title": "Germany makes COVID quarantine voluntary from May 1",
        "Full Article": "https://news.abs-cbn.com/overseas/04/05/22/germany-makes-covid-quarantine-voluntary-from-may-1",
        "Date and Time": "Apr 05 12:25 PM",
        "Author": "Agence France-Presse"
    },
    {
        "Title": "US, UK to seek Russia suspension from UN rights body",
        "Full Article": "https://news.abs-cbn.com/overseas/04/05/22/us-uk-to-seek-russia-suspension-from-un-rights-body",
        "Date and Time": "Apr 05 11:33 AM",
        "Author": "Agence France-Presse"
    },
    {
        "Title": "Kim's sister: North Korea nukes could 'eliminate' South",
        "Full Article": "https://news.abs-cbn.com/overseas/04/05/22/kims-sister-north-korea-nukes-could-eliminate-south",
        "Date and Time": "Apr 05 11:19 AM",
        "Author": "Agence France-Presse"
    },
    {
        "Title": "Satellite images show bodies in Bucha for weeks",
        "Full Article": "https://news.abs-cbn.com/overseas/04/05/22/satellite-images-show-bodies-in-bucha-for-weeks",
        "Date and Time": "Apr 05 08:30 AM",
        "Author": "Agence France-Presse"
    },
    {
        "Title": "Ukraine's Zelensky to address UN Security Council",
        "Full Article": "https://news.abs-cbn.com/overseas/04/05/22/ukraines-zelensky-to-address-un-security-council",
        "Date and Time": "Apr 05 08:17 AM",
        "Author": "Agence France-Presse"
    },
    {
        "Title": "Ukraine mayor, 4 others found dead with hands tied",
        "Full Article": "https://news.abs-cbn.com/overseas/04/05/22/ukraine-mayor-4-others-found-dead-with-hands-tied",
        "Date and Time": "Apr 05 07:03 AM",
        "Author": "Agence France-Presse"
    },
    {
        "Title": "Man charged with hate crimes for attacking Asian women",
        "Full Article": "https://news.abs-cbn.com/overseas/04/05/22/man-charged-with-hate-crimes-for-attacking-asian-women",
        "Date and Time": "Apr 05 06:57 AM",
        "Author": "Agence France-Presse"
    },
    {
        "Title": "Two-thirds of Russian troops have left Kyiv: Pentagon",
        "Full Article": "https://news.abs-cbn.com/overseas/04/05/22/two-thirds-of-russian-troops-have-left-kyiv-pentagon",
        "Date and Time": "Apr 05 06:16 AM",
        "Author": "Agence France-Presse"
    },
    {
        "Title": "Beijing tells Manila: Avoid \u2018disturbances\u2019 upsetting China policy",
        "Full Article": "https://news.abs-cbn.com/overseas/04/05/22/beijing-tells-manila-avoid-disturbances-upsetting-china-policy",
        "Date and Time": "Apr 05 04:09 AM",
        "Author": "Shi Jiangtong, South China Morning Post"
    },
    {
        "Title": "Mass graves discovered in Bucha, Ukraine",
        "Full Article": "https://news.abs-cbn.com/video/overseas/04/04/22/mass-graves-discovered-in-bucha-ukraine",
        "Date and Time": "Apr 04 10:37 PM",
        "Author": "ABS-CBN News"
    },
    {
        "Title": "Russia rejects accusations of Bucha killings",
        "Full Article": "https://news.abs-cbn.com/overseas/04/04/22/russia-rejects-accusations-of-bucha-killings",
        "Date and Time": "Apr 04 10:02 PM",
        "Author": "Agence France-Presse "
    },
    {
        "Title": "Ukraine's Zelensky appeals at the Grammys",
        "Full Article": "https://news.abs-cbn.com/overseas/multimedia/photo/04/04/22/ukraines-zelensky-appeals-at-the-grammys",
        "Date and Time": "Apr 04 07:57 PM",
        "Author": "Valerie Macon, AFP"
    },
    {
        "Title": "Shanghai defends separating COVID-hit kids from parents",
        "Full Article": "https://news.abs-cbn.com/overseas/04/04/22/shanghai-defends-separating-covid-hit-kids-from-parents",
        "Date and Time": "Apr 04 05:40 PM",
        "Author": "Agence France-Presse"
    },
    {
        "Title": "Viruses that could save millions",
        "Full Article": "https://news.abs-cbn.com/overseas/04/04/22/viruses-that-could-save-millions",
        "Date and Time": "Apr 04 03:44 PM",
        "Author": "Irakli Metrevelii, Agence France-Presse"
    },
    {
        "Title": "Hong Kong leader Carrie Lam won't seek second term",
        "Full Article": "https://news.abs-cbn.com/overseas/04/04/22/hong-kong-leader-carrie-lam-wont-seek-second-term",
        "Date and Time": "Apr 04 01:29 PM",
        "Author": "Agence France-Presse"
    },
    {
        "Title": "UN to release handbook of climate change solutions",
        "Full Article": "https://news.abs-cbn.com/overseas/04/04/22/un-to-release-handbook-of-climate-change-solutions",
        "Date and Time": "Apr 04 01:15 PM",
        "Author": "Kelly Macnamara, Agence France-Presse"
    },
    {
        "Title": "280 bodies found buried in mass graves in Ukraine",
        "Full Article": "https://news.abs-cbn.com/overseas/multimedia/photo/04/04/22/280-bodies-found-buried-in-mass-graves-in-ukraine",
        "Date and Time": "Apr 04 11:51 AM",
        "Author": "Sergei Supinsky, AFP"
    },
    {
        "Title": "At least 6 dead in California shooting",
        "Full Article": "https://news.abs-cbn.com/overseas/04/04/22/at-least-6-dead-in-california-shooting",
        "Date and Time": "Apr 04 11:13 AM",
        "Author": "Agence France-Presse "
    },
    {
        "Title": "Bodies litter Ukraine town's street of death",
        "Full Article": "https://news.abs-cbn.com/overseas/04/04/22/bodies-litter-ukraine-towns-street-of-death",
        "Date and Time": "Apr 04 10:15 AM",
        "Author": "Danny Kemp, Agence France-Presse"
    },
    {
        "Title": "Over 2,000 foreign workers to join HK private care homes",
        "Full Article": "https://news.abs-cbn.com/overseas/04/04/22/over-2000-foreign-workers-to-join-hk-private-care-homes",
        "Date and Time": "Apr 04 08:18 AM",
        "Author": "Ng Kang-chung, South China Morning Post"
    },
    {
        "Title": "Hobby pilots build Ukraine's drone fleet",
        "Full Article": "https://news.abs-cbn.com/overseas/04/04/22/hobby-pilots-build-ukraines-drone-fleet",
        "Date and Time": "Apr 04 06:40 AM",
        "Author": "Joe Stenson, Agence France-Presse"
    }
]